yingjia_common/__init__.py
yingjia_common/jiami/__init__.py
yingjia_common/log/__init__.py
yingjia_common/log/log_opt.py
yingjia_common/message/__init__.py
yingjia_common/message/dingding.py
yingjia_common/test/HTMLTestRunner.py
yingjia_common/test/__init__.py
yingjia_common/test/test_demo.py
yingjia_common/time/__init__.py
yingjia_common-1.0.6.dist-info/LICENSE
yingjia_common-1.0.6.dist-info/METADATA
yingjia_common-1.0.6.dist-info/WHEEL
yingjia_common-1.0.6.dist-info/top_level.txt
yingjia_common-1.0.6.dist-info/RECORD
